{
  "$schema": "https://raw.githubusercontent.com/spdx/spdx-spec/v2.2.1/schemas/spdx-schema.json",
  "spdxVersion": "SPDX-2.2",
  "dataLicense": "CC0-1.0",
  "SPDXID": "SPDXRef-DOCUMENT",
  "documentNamespace": "https://spdx.org/spdxdocs/vcpkg-pkgconfig-get-modules-x64-windows-2023-09-06-da36680b-45fc-4495-9b6f-06ff28691d7a",
  "name": "vcpkg-pkgconfig-get-modules:x64-windows@2023-09-06 57a613c66e6baf97753be361f6bd8f37147e0551596a077f5d5ba6d7e3159533",
  "creationInfo": {
    "creators": [
      "Tool: vcpkg-2024-09-18-5f5da308dd1dd3cc49641c60eafff176e248a9dd"
    ],
    "created": "2024-09-28T05:05:55Z"
  },
  "relationships": [
    {
      "spdxElementId": "SPDXRef-port",
      "relationshipType": "GENERATES",
      "relatedSpdxElement": "SPDXRef-binary"
    },
    {
      "spdxElementId": "SPDXRef-port",
      "relationshipType": "CONTAINS",
      "relatedSpdxElement": "SPDXRef-file-0"
    },
    {
      "spdxElementId": "SPDXRef-port",
      "relationshipType": "CONTAINS",
      "relatedSpdxElement": "SPDXRef-file-1"
    },
    {
      "spdxElementId": "SPDXRef-port",
      "relationshipType": "CONTAINS",
      "relatedSpdxElement": "SPDXRef-file-2"
    },
    {
      "spdxElementId": "SPDXRef-port",
      "relationshipType": "CONTAINS",
      "relatedSpdxElement": "SPDXRef-file-3"
    },
    {
      "spdxElementId": "SPDXRef-binary",
      "relationshipType": "GENERATED_FROM",
      "relatedSpdxElement": "SPDXRef-port"
    },
    {
      "spdxElementId": "SPDXRef-file-0",
      "relationshipType": "CONTAINED_BY",
      "relatedSpdxElement": "SPDXRef-port"
    },
    {
      "spdxElementId": "SPDXRef-file-1",
      "relationshipType": "CONTAINED_BY",
      "relatedSpdxElement": "SPDXRef-port"
    },
    {
      "spdxElementId": "SPDXRef-file-2",
      "relationshipType": "CONTAINED_BY",
      "relatedSpdxElement": "SPDXRef-port"
    },
    {
      "spdxElementId": "SPDXRef-file-3",
      "relationshipType": "CONTAINED_BY",
      "relatedSpdxElement": "SPDXRef-port"
    }
  ],
  "packages": [
    {
      "name": "vcpkg-pkgconfig-get-modules",
      "SPDXID": "SPDXRef-port",
      "versionInfo": "2023-09-06",
      "downloadLocation": "git+https://github.com/microsoft/vcpkg@365f7303c0f9fe13458a62e7e4998760e6d918a4",
      "licenseConcluded": "MIT",
      "licenseDeclared": "NOASSERTION",
      "copyrightText": "NOASSERTION",
      "comment": "This is the port (recipe) consumed by vcpkg."
    },
    {
      "name": "vcpkg-pkgconfig-get-modules:x64-windows",
      "SPDXID": "SPDXRef-binary",
      "versionInfo": "57a613c66e6baf97753be361f6bd8f37147e0551596a077f5d5ba6d7e3159533",
      "downloadLocation": "NONE",
      "licenseConcluded": "MIT",
      "licenseDeclared": "NOASSERTION",
      "copyrightText": "NOASSERTION",
      "comment": "This is a binary package built by vcpkg."
    }
  ],
  "files": [
    {
      "fileName": "./C:/Users/jesse/AppData/Local/vcpkg/registries/git-trees/365f7303c0f9fe13458a62e7e4998760e6d918a4/portfile.cmake",
      "SPDXID": "SPDXRef-file-0",
      "checksums": [
        {
          "algorithm": "SHA256",
          "checksumValue": "0d6a2e621ea1e349ae1202a3530adbdc339eeefd8ef874a85f197219d39e986f"
        }
      ],
      "licenseConcluded": "NOASSERTION",
      "copyrightText": "NOASSERTION"
    },
    {
      "fileName": "./C:/Users/jesse/AppData/Local/vcpkg/registries/git-trees/365f7303c0f9fe13458a62e7e4998760e6d918a4/vcpkg-port-config.cmake",
      "SPDXID": "SPDXRef-file-1",
      "checksums": [
        {
          "algorithm": "SHA256",
          "checksumValue": "af32777ec0921985699f91ee097b889e32813aede0bafc860521f11e47571cdc"
        }
      ],
      "licenseConcluded": "NOASSERTION",
      "copyrightText": "NOASSERTION"
    },
    {
      "fileName": "./C:/Users/jesse/AppData/Local/vcpkg/registries/git-trees/365f7303c0f9fe13458a62e7e4998760e6d918a4/vcpkg.json",
      "SPDXID": "SPDXRef-file-2",
      "checksums": [
        {
          "algorithm": "SHA256",
          "checksumValue": "d8468317e1d14e9fa033091a3349492b348ba5698e442e0c3c1a608406a66da7"
        }
      ],
      "licenseConcluded": "NOASSERTION",
      "copyrightText": "NOASSERTION"
    },
    {
      "fileName": "./C:/Users/jesse/AppData/Local/vcpkg/registries/git-trees/365f7303c0f9fe13458a62e7e4998760e6d918a4/x_vcpkg_pkgconfig_get_modules.cmake",
      "SPDXID": "SPDXRef-file-3",
      "checksums": [
        {
          "algorithm": "SHA256",
          "checksumValue": "25c857d5aba3b5922e1547cd7787f5b283c54a7aaae4d8561bb7b339fd6a0707"
        }
      ],
      "licenseConcluded": "NOASSERTION",
      "copyrightText": "NOASSERTION"
    }
  ]
}
